{
  "id": "dbjjaiiifhkgdkhhfnefgcjmbhniknmk",
  "name": "PartsCheck",
  "riskScore": 1,
  "riskImpact": 1,
  "riskLikelihood": 1,
  "logo": "https://lh3.googleusercontent.com/Gp-k1Cz7IDfj2LwkwGJMEsqK7UZ4zhKkNwWvvyGZvJsYIkTvx-ItMt9tjQkOy5A2chD6CnGFYrGvTjZjL_6tbYUf",
  "fetchId": 20240308,
  "version": 1.07,
  "ratingValue": 0,
  "ratingCount": 0,
  "description": "PartsCheck provides individualised support to our clients.",
  "itemCategory": "extension",
  "userCount": 62,
  "category": "productivity/workflow",
  "lastUpdate": "2020-02-04",
  "creationDate": "2020-02-04",
  "size": 857088,
  "author": "https://www.partscheck.com.au",
  "smallBanner": "https://lh3.googleusercontent.com/c3bBk0UKr9_VU20Ouo2VM7MXasKRctPjxYru1TDjgeN48IRnyfD1Gma1nnE2wduDO7qT6xjMxfDOnDR33GnxUQ6Dbw",
  "marqueeBanner": null,
  "email": "support@partscheck.com.au",
  "emailIsInvalid": null,
  "supportedLanguages": "[\"en\"]",
  "website": "http://www.partscheck.com.au",
  "url": "https://chromewebstore.google.com/detail/partscheck/dbjjaiiifhkgdkhhfnefgcjmbhniknmk",
  "numScreenshots": 3,
  "numVideos": 1,
  "downloadUrl": "https://chrome-stats.com/api/download?id=dbjjaiiifhkgdkhhfnefgcjmbhniknmk&version=1.07&type=CRX",
  "isFeatured": null,
  "paymentType": "free",
  "privacyPolicyUrl": "http://www.partscheck.com.au/global/privacy.php",
  "resurrectionDate": null,
  "previousObsoleteDate": null,
  "publisherAddress": "8/149 Bluestone Circuit, \nSeventeen Mile Rocks, Qld 4073\nAustralia",
  "publisherCountry": "Australia",
  "isTrustedPublisher": null,
  "isMature": null,
  "byGoogle": null,
  "helpUrl": "http://www.partscheck.com.au/global/contact-partscheck.php",
  "isUnlisted": null,
  "extension-rank": 55064,
  "theme-rank": null,
  "application-rank": null,
  "overall-rank": 72212,
  "manifest_manifest_version": 2,
  "manifest_has_browser_action": true,
  "manifest_has_page_action": null,
  "manifest_minimum_chrome_version": null,
  "manifest_override_homepage": null,
  "manifest_override_search_provider": null,
  "manifest_override_bookmarks": null,
  "manifest_override_history": null,
  "manifest_override_newtab": null,
  "manifest_startup_pages": null,
  "manifest_has_devtools_page": null,
  "manifest_has_commands": null,
  "manifest_has_content_scripts": true,
  "manifest_has_oauth": null,
  "manifest_has_file_browser_handlers": null,
  "manifest_has_nacl_modules": null,
  "manifest_offline_enabled": null,
  "manifest_omnibox_keyword": null,
  "manifest_optional_permissions": null,
  "manifest_permissions": "declarativeContent,storage,alarms",
  "manifest_host_permissions": null,
  "manifest_optional_host_permissions": null,
  "manifest_num_site_permissions": 2,
  "manifest_web_accessible_resources": null
}