{
  "id": "fdhgalhnniglmblkplkgncjhffnolaje",
  "name": "Compartir escritorio para Eternity.online",
  "riskScore": 2,
  "riskImpact": 2,
  "riskLikelihood": 2,
  "logo": "https://lh3.googleusercontent.com/2SxlLGg_9trq4S_cVwnIXZqXozRuYZMZXgv84vGoQNUifzcaTypMil1qePcf5nol5TcF6Sgkf1Ov1baMtqzMbb3M-w",
  "fetchId": 20240308,
  "version": "0.2.8.20",
  "ratingValue": 0,
  "ratingCount": 0,
  "description": "Te permite compartir tu escritorio con los demas dentro de una videoconferencia de Eternity Online.",
  "itemCategory": "extension",
  "userCount": 9,
  "category": "lifestyle/social",
  "lastUpdate": "2019-01-16",
  "creationDate": "2019-01-16",
  "size": 23726,
  "author": "https://cam.eternity.online",
  "smallBanner": "https://lh3.googleusercontent.com/z1kg6uDXG659QHdaQSjYzY__lx_lfgspYGSxJGVh2eu5Osb5h5SldIAzlhXxAApWsY9231VKZ-npnVODAKCPhDOK",
  "marqueeBanner": null,
  "email": "info@eternity.online",
  "emailIsInvalid": null,
  "supportedLanguages": "[\"es\"]",
  "website": "https://www.eternity.online",
  "url": "https://chromewebstore.google.com/detail/compartir-escritorio-para/fdhgalhnniglmblkplkgncjhffnolaje",
  "numScreenshots": 1,
  "numVideos": null,
  "downloadUrl": "https://chrome-stats.com/api/download?id=fdhgalhnniglmblkplkgncjhffnolaje&version=0.2.8.20&type=CRX",
  "isFeatured": null,
  "paymentType": "free",
  "privacyPolicyUrl": "https://eternity.online/aviso-legal-politica-privacidad-cookies",
  "resurrectionDate": null,
  "previousObsoleteDate": null,
  "publisherAddress": "C/ La Granja Nº 14 Bajo A\nPalazuelos de Eresma, Segovia 40194\nEspaña",
  "publisherCountry": "España",
  "isTrustedPublisher": null,
  "isMature": null,
  "byGoogle": null,
  "helpUrl": null,
  "isUnlisted": null,
  "extension-rank": 86249,
  "theme-rank": null,
  "application-rank": null,
  "overall-rank": 113982,
  "manifest_manifest_version": 2,
  "manifest_has_browser_action": null,
  "manifest_has_page_action": null,
  "manifest_minimum_chrome_version": 34,
  "manifest_override_homepage": null,
  "manifest_override_search_provider": null,
  "manifest_override_bookmarks": null,
  "manifest_override_history": null,
  "manifest_override_newtab": null,
  "manifest_startup_pages": null,
  "manifest_has_devtools_page": null,
  "manifest_has_commands": null,
  "manifest_has_content_scripts": null,
  "manifest_has_oauth": null,
  "manifest_has_file_browser_handlers": null,
  "manifest_has_nacl_modules": null,
  "manifest_offline_enabled": null,
  "manifest_omnibox_keyword": null,
  "manifest_optional_permissions": null,
  "manifest_permissions": "desktopCapture",
  "manifest_host_permissions": null,
  "manifest_optional_host_permissions": null,
  "manifest_num_site_permissions": null,
  "manifest_web_accessible_resources": null
}