{
  "id": "flhjcfbefejnckkajogdnmkmlbjnecbf",
  "name": "Zone Dispatch Plugin",
  "riskScore": 2,
  "riskImpact": 2,
  "riskLikelihood": 1,
  "logo": "https://lh3.googleusercontent.com/BnCdShyq01ENF_qBbWim_87l6Tl6NdauR5K7lx057C3bZa-qR_nyJcQ2rDFE97Gj_TDdTCtLCQChjMYu0LkEKDSjHQ",
  "fetchId": 20240308,
  "version": 1.2,
  "ratingValue": 0,
  "ratingCount": 0,
  "description": "Allows use of Motorola Solutions Dispatch plugin Manifest3",
  "itemCategory": "extension",
  "userCount": 14,
  "category": "lifestyle/social",
  "lastUpdate": "2022-10-23",
  "creationDate": "2022-10-22",
  "size": 36536,
  "author": "sqvz66",
  "smallBanner": null,
  "marqueeBanner": null,
  "email": "sqvz66@motorolasolutions.com",
  "emailIsInvalid": null,
  "supportedLanguages": "[\"en-US\"]",
  "website": "https://wds.wifiidcsqaonprem.com/WebDispatcher/idmui/index.html",
  "url": "https://chromewebstore.google.com/detail/zone-dispatch-plugin/flhjcfbefejnckkajogdnmkmlbjnecbf",
  "numScreenshots": 1,
  "numVideos": null,
  "downloadUrl": "https://chrome-stats.com/api/download?id=flhjcfbefejnckkajogdnmkmlbjnecbf&version=1.2&type=CRX",
  "isFeatured": null,
  "paymentType": "free",
  "privacyPolicyUrl": null,
  "resurrectionDate": null,
  "previousObsoleteDate": null,
  "publisherAddress": null,
  "publisherCountry": null,
  "isTrustedPublisher": null,
  "isMature": null,
  "byGoogle": null,
  "helpUrl": "https://wds.wifiidcsqaonprem.com/WebDispatcher/idmui/index.html",
  "isUnlisted": null,
  "extension-rank": 78541,
  "theme-rank": null,
  "application-rank": null,
  "overall-rank": 103835,
  "manifest_manifest_version": 3,
  "manifest_has_browser_action": null,
  "manifest_has_page_action": null,
  "manifest_minimum_chrome_version": null,
  "manifest_override_homepage": null,
  "manifest_override_search_provider": null,
  "manifest_override_bookmarks": null,
  "manifest_override_history": null,
  "manifest_override_newtab": null,
  "manifest_startup_pages": null,
  "manifest_has_devtools_page": null,
  "manifest_has_commands": null,
  "manifest_has_content_scripts": true,
  "manifest_has_oauth": null,
  "manifest_has_file_browser_handlers": null,
  "manifest_has_nacl_modules": null,
  "manifest_offline_enabled": null,
  "manifest_omnibox_keyword": null,
  "manifest_optional_permissions": null,
  "manifest_permissions": "nativeMessaging",
  "manifest_host_permissions": null,
  "manifest_optional_host_permissions": null,
  "manifest_num_site_permissions": null,
  "manifest_web_accessible_resources": "[{\"resources\":[\"wyrmhole.js\",\"wyrmhole-page.js\",\"FireBreathPromise.js\",\"firewyrm.js\",\"insertJs.js\"],\"matches\":[\"<all_urls>\"]}]"
}