{
  "id": "gcjdaonlebgdmlckjiincemimaolbccc",
  "name": "RZAM",
  "riskScore": 1,
  "riskImpact": 3,
  "riskLikelihood": 1,
  "logo": "https://lh3.googleusercontent.com/VXQEPY5Rv_btpqYTbKHLsJK2wbiViMr6nYILz7FfdCFDSQ3EVNahWNSS46ND-P4M5TwOLcbD-BiDmJ1hqpmaWKISzw",
  "fetchId": 20240308,
  "version": "1.1.4",
  "ratingValue": 5,
  "ratingCount": 2,
  "description": "RZAM helps you browse the web safely by blocking Malicious sites. Developed by Dubai Electronic Security Center",
  "itemCategory": "extension",
  "userCount": 384,
  "category": "make_chrome_yours/privacy",
  "lastUpdate": "2024-02-29",
  "creationDate": "2023-06-06",
  "size": 1866465,
  "author": "Dubai Electronic Security Center",
  "smallBanner": null,
  "marqueeBanner": null,
  "email": "rzam.support@desc.gov.ae",
  "emailIsInvalid": null,
  "supportedLanguages": "[\"en\"]",
  "website": "https://desc.gov.ae/rzam/",
  "url": "https://chromewebstore.google.com/detail/rzam/gcjdaonlebgdmlckjiincemimaolbccc",
  "numScreenshots": 5,
  "numVideos": null,
  "downloadUrl": "https://chrome-stats.com/api/download?id=gcjdaonlebgdmlckjiincemimaolbccc&version=1.1.4&type=CRX",
  "isFeatured": true,
  "paymentType": "free",
  "privacyPolicyUrl": "https://desc.gov.ae/rzam/privacy-policy/index.html",
  "resurrectionDate": null,
  "previousObsoleteDate": null,
  "publisherAddress": null,
  "publisherCountry": null,
  "isTrustedPublisher": true,
  "isMature": null,
  "byGoogle": null,
  "helpUrl": "https://desc.gov.ae/rzam/",
  "isUnlisted": null,
  "extension-rank": 32386,
  "theme-rank": null,
  "application-rank": null,
  "overall-rank": 41251,
  "manifest_manifest_version": 3,
  "manifest_has_browser_action": null,
  "manifest_has_page_action": null,
  "manifest_minimum_chrome_version": null,
  "manifest_override_homepage": null,
  "manifest_override_search_provider": null,
  "manifest_override_bookmarks": null,
  "manifest_override_history": null,
  "manifest_override_newtab": null,
  "manifest_startup_pages": null,
  "manifest_has_devtools_page": null,
  "manifest_has_commands": null,
  "manifest_has_content_scripts": null,
  "manifest_has_oauth": null,
  "manifest_has_file_browser_handlers": null,
  "manifest_has_nacl_modules": null,
  "manifest_offline_enabled": null,
  "manifest_omnibox_keyword": null,
  "manifest_optional_permissions": null,
  "manifest_permissions": "activeTab,tabs,storage,unlimitedStorage,declarativeNetRequest,webNavigation",
  "manifest_host_permissions": "<all_urls>",
  "manifest_optional_host_permissions": null,
  "manifest_num_site_permissions": "NaN",
  "manifest_web_accessible_resources": "[{\"resources\":[\"rzam/*\"],\"extension_ids\":[\"nbagmjhdejnhfnahpolohejlfafljjbe\"]}]"
}