{
  "id": "jiieejiponjbbnldnklcbamkembhhpka",
  "name": "Exzo Wallet",
  "riskScore": 2,
  "riskImpact": 2,
  "riskLikelihood": 2,
  "logo": "https://lh3.googleusercontent.com/L0crFjbdR2SXZYPk7V5qxWKLz__NxaVDtb_AMo_iedJJmaUwzHR2T7rj3JcoNlfp_zWmGH0Q7n8BVDkYf9cfWgagdw",
  "fetchId": 20240308,
  "version": 1,
  "ratingValue": 4.978070175438597,
  "ratingCount": 228,
  "description": "A Secure & Private Web3 Wallet for your Crypto, NFT's, and DeFi Adventures!",
  "itemCategory": "extension",
  "userCount": 314,
  "category": "productivity/workflow",
  "lastUpdate": "2024-02-20",
  "creationDate": "2023-04-15",
  "size": 20541604,
  "author": "https://exzo.network",
  "smallBanner": "https://lh3.googleusercontent.com/N6pkAPkogHHiqH1CZafcmIEo054B0Asz5r9mv8L6Zf2vEmuraCwTZsXMIkVO1xO3D7jcsXJ_EvyNmatR_FQpJIdTSyA",
  "marqueeBanner": null,
  "email": "support@exzo.network",
  "emailIsInvalid": null,
  "supportedLanguages": "[\"en-US\"]",
  "website": "https://exzo.network",
  "url": "https://chromewebstore.google.com/detail/exzo-wallet/jiieejiponjbbnldnklcbamkembhhpka",
  "numScreenshots": 4,
  "numVideos": 1,
  "downloadUrl": "https://chrome-stats.com/api/download?id=jiieejiponjbbnldnklcbamkembhhpka&version=1.0&type=CRX",
  "isFeatured": null,
  "paymentType": "free",
  "privacyPolicyUrl": "https://www.exzo.network/privacy",
  "resurrectionDate": null,
  "previousObsoleteDate": null,
  "publisherAddress": "62 NE 167th St\nUnit 1202\nMiami, FL 33162\nUS",
  "publisherCountry": "US",
  "isTrustedPublisher": null,
  "isMature": null,
  "byGoogle": null,
  "helpUrl": "https://t.me/Exzo_Network",
  "isUnlisted": true,
  "extension-rank": 34577,
  "theme-rank": null,
  "application-rank": null,
  "overall-rank": 44258,
  "manifest_manifest_version": 3,
  "manifest_has_browser_action": null,
  "manifest_has_page_action": null,
  "manifest_minimum_chrome_version": null,
  "manifest_override_homepage": null,
  "manifest_override_search_provider": null,
  "manifest_override_bookmarks": null,
  "manifest_override_history": null,
  "manifest_override_newtab": null,
  "manifest_startup_pages": null,
  "manifest_has_devtools_page": null,
  "manifest_has_commands": null,
  "manifest_has_content_scripts": true,
  "manifest_has_oauth": null,
  "manifest_has_file_browser_handlers": null,
  "manifest_has_nacl_modules": null,
  "manifest_offline_enabled": null,
  "manifest_omnibox_keyword": null,
  "manifest_optional_permissions": null,
  "manifest_permissions": "activeTab,storage,notifications,alarms",
  "manifest_host_permissions": "file://*/*,http://*/*,https://*/*",
  "manifest_optional_host_permissions": null,
  "manifest_num_site_permissions": "NaN",
  "manifest_web_accessible_resources": "[{\"resources\":[\"blankProvider.js\",\"keep-alive\"],\"matches\":[\"<all_urls>\"]}]"
}