{
  "id": "llpepekkleeoeiloijhcafgpjdnhhcbl",
  "name": "YouTube Music Last.fm Scrobbler",
  "riskScore": 3,
  "riskImpact": 3,
  "riskLikelihood": 1,
  "logo": "https://lh3.googleusercontent.com/x-Fk56WkmpcrA_0UN8QKpkjrcCMRAP-THsXmlMGRlTo2KVMHSIFeQyMP2Xze4GzR9B4zXe1z8lWAm64CN3CTHGGk0w",
  "fetchId": 20240308,
  "version": "2.0.2",
  "ratingValue": 3.9748427672955975,
  "ratingCount": 318,
  "description": "Scrobbles songs from YouTube Music or Google Play to Last.fm",
  "itemCategory": "extension",
  "userCount": 10000,
  "category": "lifestyle/social",
  "lastUpdate": "2022-01-27",
  "creationDate": "2020-05-30",
  "size": 141312,
  "author": "newgiin",
  "smallBanner": null,
  "marqueeBanner": null,
  "email": "atnguyen4@gmail.com",
  "emailIsInvalid": null,
  "supportedLanguages": "[\"en-US\"]",
  "website": null,
  "url": "https://chromewebstore.google.com/detail/youtube-music-lastfm-scro/llpepekkleeoeiloijhcafgpjdnhhcbl",
  "numScreenshots": 2,
  "numVideos": null,
  "downloadUrl": "https://chrome-stats.com/api/download?id=llpepekkleeoeiloijhcafgpjdnhhcbl&version=2.0.2&type=CRX",
  "isFeatured": null,
  "paymentType": "free",
  "privacyPolicyUrl": null,
  "resurrectionDate": null,
  "previousObsoleteDate": null,
  "publisherAddress": null,
  "publisherCountry": null,
  "isTrustedPublisher": null,
  "isMature": null,
  "byGoogle": null,
  "helpUrl": "https://github.com/newgiin/cloudplayer-scrobbler/issues",
  "isUnlisted": null,
  "extension-rank": 5934,
  "theme-rank": null,
  "application-rank": null,
  "overall-rank": 7261,
  "manifest_manifest_version": 2,
  "manifest_has_browser_action": true,
  "manifest_has_page_action": null,
  "manifest_minimum_chrome_version": null,
  "manifest_override_homepage": null,
  "manifest_override_search_provider": null,
  "manifest_override_bookmarks": null,
  "manifest_override_history": null,
  "manifest_override_newtab": null,
  "manifest_startup_pages": null,
  "manifest_has_devtools_page": null,
  "manifest_has_commands": true,
  "manifest_has_content_scripts": true,
  "manifest_has_oauth": null,
  "manifest_has_file_browser_handlers": null,
  "manifest_has_nacl_modules": null,
  "manifest_offline_enabled": null,
  "manifest_omnibox_keyword": null,
  "manifest_optional_permissions": null,
  "manifest_permissions": null,
  "manifest_host_permissions": null,
  "manifest_optional_host_permissions": null,
  "manifest_num_site_permissions": 4,
  "manifest_web_accessible_resources": "[\"html/lastfm_callback.html\"]"
}