{
  "id": "mmaneaofefbdhecclkaokfmclgcagdah",
  "name": "Gravelord Nito",
  "riskScore": 0,
  "riskImpact": 0,
  "riskLikelihood": 1,
  "logo": "https://lh3.googleusercontent.com/z3l_A2lew0BUq7YZxYT7Z23jml_t7xQpV2wOTkM1xOTGs9CQxMgrOZ0I3OYjL2A-cz6LZ8KKOP1Wd4ZbwG3MmIXlXQ",
  "fetchId": 20240308,
  "version": 1,
  "ratingValue": 4.704918032786885,
  "ratingCount": 183,
  "description": "Dark Souls' Gravelord Nito Chrome Theme",
  "itemCategory": "theme",
  "userCount": 398,
  "category": null,
  "lastUpdate": "2012-07-21",
  "creationDate": "2012-07-20",
  "size": 6364856,
  "author": "ikarilink",
  "smallBanner": "https://lh3.googleusercontent.com/fIdqo4m5NAToUZM-ptsnvaCLtQlYPe5RHDwEDKp_u4O_XqZXsV8enu5rht-6VGcefyQ0SrlbMGcXKbNV2cSB3r-s",
  "marqueeBanner": null,
  "email": null,
  "emailIsInvalid": null,
  "supportedLanguages": "[\"en-US\"]",
  "website": null,
  "url": "https://chromewebstore.google.com/detail/gravelord-nito/mmaneaofefbdhecclkaokfmclgcagdah",
  "numScreenshots": 1,
  "numVideos": null,
  "downloadUrl": "https://chrome-stats.com/api/download?id=mmaneaofefbdhecclkaokfmclgcagdah&version=1&type=CRX",
  "isFeatured": null,
  "paymentType": "free",
  "privacyPolicyUrl": null,
  "resurrectionDate": null,
  "previousObsoleteDate": null,
  "publisherAddress": null,
  "publisherCountry": null,
  "isTrustedPublisher": null,
  "isMature": null,
  "byGoogle": null,
  "helpUrl": null,
  "isUnlisted": null,
  "extension-rank": null,
  "theme-rank": 3739,
  "application-rank": null,
  "overall-rank": 40698,
  "manifest_manifest_version": null,
  "manifest_has_browser_action": null,
  "manifest_has_page_action": null,
  "manifest_minimum_chrome_version": null,
  "manifest_override_homepage": null,
  "manifest_override_search_provider": null,
  "manifest_override_bookmarks": null,
  "manifest_override_history": null,
  "manifest_override_newtab": null,
  "manifest_startup_pages": null,
  "manifest_has_devtools_page": null,
  "manifest_has_commands": null,
  "manifest_has_content_scripts": null,
  "manifest_has_oauth": null,
  "manifest_has_file_browser_handlers": null,
  "manifest_has_nacl_modules": null,
  "manifest_offline_enabled": null,
  "manifest_omnibox_keyword": null,
  "manifest_optional_permissions": null,
  "manifest_permissions": null,
  "manifest_host_permissions": null,
  "manifest_optional_host_permissions": null,
  "manifest_num_site_permissions": null,
  "manifest_web_accessible_resources": null
}