{
  "id": "okikilakaimaefihfmnkhocmakgbecbo",
  "name": "UW Off-Campus Reading",
  "riskScore": 1,
  "riskImpact": 1,
  "riskLikelihood": 2,
  "logo": "https://lh3.googleusercontent.com/F1Zt2pD8wrr_cW0EX2ox9p8TiV56t4jArLheYXqR_T6Jy9CyPPTPIQuI5ZM-45jDqmLpbsfc7_Mw-KwSi385hr0Wig",
  "fetchId": 20240308,
  "version": 0.1,
  "ratingValue": 0,
  "ratingCount": 0,
  "description": "Quality of life improvement to allow University of Washington students to access papers from the off-campus website.",
  "itemCategory": "extension",
  "userCount": 0,
  "category": "productivity/workflow",
  "lastUpdate": "2023-04-08",
  "creationDate": "2023-04-08",
  "size": 4383,
  "author": "Thomas Schweizer",
  "smallBanner": null,
  "marqueeBanner": null,
  "email": "tschweizer.dev@gmail.com",
  "emailIsInvalid": null,
  "supportedLanguages": "[\"en\"]",
  "website": "https://github.com/Thomsch/uw-offcampus-reading",
  "url": "https://chromewebstore.google.com/detail/uw-off-campus-reading/okikilakaimaefihfmnkhocmakgbecbo",
  "numScreenshots": 1,
  "numVideos": null,
  "downloadUrl": "https://chrome-stats.com/api/download?id=okikilakaimaefihfmnkhocmakgbecbo&version=0.1&type=CRX",
  "isFeatured": null,
  "paymentType": "free",
  "privacyPolicyUrl": null,
  "resurrectionDate": null,
  "previousObsoleteDate": null,
  "publisherAddress": null,
  "publisherCountry": null,
  "isTrustedPublisher": null,
  "isMature": null,
  "byGoogle": null,
  "helpUrl": "https://github.com/Thomsch/uw-offcampus-reading",
  "isUnlisted": null,
  "extension-rank": 116182,
  "theme-rank": null,
  "application-rank": null,
  "overall-rank": 158026,
  "manifest_manifest_version": 3,
  "manifest_has_browser_action": null,
  "manifest_has_page_action": null,
  "manifest_minimum_chrome_version": null,
  "manifest_override_homepage": null,
  "manifest_override_search_provider": null,
  "manifest_override_bookmarks": null,
  "manifest_override_history": null,
  "manifest_override_newtab": null,
  "manifest_startup_pages": null,
  "manifest_has_devtools_page": null,
  "manifest_has_commands": null,
  "manifest_has_content_scripts": true,
  "manifest_has_oauth": null,
  "manifest_has_file_browser_handlers": null,
  "manifest_has_nacl_modules": null,
  "manifest_offline_enabled": null,
  "manifest_omnibox_keyword": null,
  "manifest_optional_permissions": null,
  "manifest_permissions": null,
  "manifest_host_permissions": null,
  "manifest_optional_host_permissions": null,
  "manifest_num_site_permissions": null,
  "manifest_web_accessible_resources": null
}