{
  "id": "ghjkcholelkaibjpjpnlohnppfoondne",
  "name": "Aurora Grass",
  "riskScore": 0,
  "riskImpact": 0,
  "riskLikelihood": 1,
  "logo": null,
  "fetchId": 20240308,
  "version": "1.0.1",
  "ratingValue": 4.230769230769231,
  "ratingCount": 65,
  "description": "A Simple and elegant theme for google chrome.\r\na black toolbar and a green grass frame.in a \"Aero\" Style.\r\nif you want more aurora…",
  "itemCategory": "theme",
  "userCount": 18,
  "category": null,
  "lastUpdate": "2011-06-08",
  "creationDate": "2010-01-10",
  "size": 1289748,
  "author": "elexpu",
  "smallBanner": null,
  "marqueeBanner": null,
  "email": null,
  "emailIsInvalid": null,
  "supportedLanguages": "[]",
  "website": "http://www.taringa.net/posts/downloads/4349445/Aurora-Themes-para-Google-Chrome-[en-formato-crx].html",
  "url": "https://chromewebstore.google.com/detail/empty-title/ghjkcholelkaibjpjpnlohnppfoondne",
  "numScreenshots": 1,
  "numVideos": null,
  "downloadUrl": "https://chrome-stats.com/api/download?id=ghjkcholelkaibjpjpnlohnppfoondne&version=1.0.1&type=CRX",
  "isFeatured": null,
  "paymentType": "free",
  "privacyPolicyUrl": null,
  "resurrectionDate": null,
  "previousObsoleteDate": null,
  "publisherAddress": null,
  "publisherCountry": null,
  "isTrustedPublisher": null,
  "isMature": null,
  "byGoogle": null,
  "helpUrl": null,
  "isUnlisted": null,
  "extension-rank": null,
  "theme-rank": 13452,
  "application-rank": null,
  "overall-rank": 96938,
  "manifest_manifest_version": null,
  "manifest_has_browser_action": null,
  "manifest_has_page_action": null,
  "manifest_minimum_chrome_version": null,
  "manifest_override_homepage": null,
  "manifest_override_search_provider": null,
  "manifest_override_bookmarks": null,
  "manifest_override_history": null,
  "manifest_override_newtab": null,
  "manifest_startup_pages": null,
  "manifest_has_devtools_page": null,
  "manifest_has_commands": null,
  "manifest_has_content_scripts": null,
  "manifest_has_oauth": null,
  "manifest_has_file_browser_handlers": null,
  "manifest_has_nacl_modules": null,
  "manifest_offline_enabled": null,
  "manifest_omnibox_keyword": null,
  "manifest_optional_permissions": null,
  "manifest_permissions": null,
  "manifest_host_permissions": null,
  "manifest_optional_host_permissions": null,
  "manifest_num_site_permissions": null,
  "manifest_web_accessible_resources": null
}