{
  "id": "keenhcnmdmjjhincpilijphpiohdppno",
  "name": "5ire Wallet",
  "riskScore": 3,
  "riskImpact": 3,
  "riskLikelihood": 2,
  "logo": "https://lh3.googleusercontent.com/bzCjQnWJ16zRDdLj9lxyV6N8Sjs2-VjmEluA0i2xpRz691aqtH9fCX49SemGw_aXAAMCr1tqvINTGOkENYOmSuLpvQ",
  "fetchId": 20240308,
  "version": "0.2.0",
  "ratingValue": 3.6666666666666665,
  "ratingCount": 132,
  "description": "5ire Wallet in your browser compatible with both Native and EVM chains.",
  "itemCategory": "extension",
  "userCount": 50000,
  "category": "productivity/workflow",
  "lastUpdate": "2024-01-31",
  "creationDate": "2023-04-10",
  "size": 5085594,
  "author": "5ire Engineering",
  "smallBanner": null,
  "marqueeBanner": null,
  "email": "technology@5ire.org",
  "emailIsInvalid": null,
  "supportedLanguages": "[\"en-US\"]",
  "website": "https://www.5ire.org",
  "url": "https://chromewebstore.google.com/detail/5ire-wallet/keenhcnmdmjjhincpilijphpiohdppno",
  "numScreenshots": 5,
  "numVideos": null,
  "downloadUrl": "https://chrome-stats.com/api/download?id=keenhcnmdmjjhincpilijphpiohdppno&version=0.2.0&type=CRX",
  "isFeatured": null,
  "paymentType": "free",
  "privacyPolicyUrl": "https://5ire-wallet-extension.s3.amazonaws.com/5ire-wallet-extension-privacy-policy.pdf",
  "resurrectionDate": null,
  "previousObsoleteDate": null,
  "publisherAddress": null,
  "publisherCountry": null,
  "isTrustedPublisher": null,
  "isMature": null,
  "byGoogle": null,
  "helpUrl": null,
  "isUnlisted": null,
  "extension-rank": 3246,
  "theme-rank": null,
  "application-rank": null,
  "overall-rank": 3901,
  "manifest_manifest_version": 3,
  "manifest_has_browser_action": null,
  "manifest_has_page_action": null,
  "manifest_minimum_chrome_version": null,
  "manifest_override_homepage": null,
  "manifest_override_search_provider": null,
  "manifest_override_bookmarks": null,
  "manifest_override_history": null,
  "manifest_override_newtab": null,
  "manifest_startup_pages": null,
  "manifest_has_devtools_page": null,
  "manifest_has_commands": true,
  "manifest_has_content_scripts": true,
  "manifest_has_oauth": null,
  "manifest_has_file_browser_handlers": null,
  "manifest_has_nacl_modules": null,
  "manifest_offline_enabled": null,
  "manifest_omnibox_keyword": null,
  "manifest_optional_permissions": null,
  "manifest_permissions": "activeTab,clipboardWrite,notifications,scripting,storage,tabs",
  "manifest_host_permissions": "http://*/,https://*/",
  "manifest_optional_host_permissions": null,
  "manifest_num_site_permissions": "NaN",
  "manifest_web_accessible_resources": null
}