{
  "id": "adofikeojceeapelplfkcgommdhnocdi",
  "name": "Hello World!",
  "riskScore": 0,
  "riskImpact": 0,
  "riskLikelihood": 2,
  "logo": "https://lh3.googleusercontent.com/iMnUkWBBn88xSHRzof2zTMwU4F_Db7f2ep1YjqL-zIgKuPJ3uL8FjbVNU0nZoo7amGtZO2W48M5fr1gAON5qS7yQ",
  "fetchId": 20240308,
  "version": 0.1,
  "ratingValue": 0,
  "ratingCount": 0,
  "description": "My first Chrome App.",
  "itemCategory": "application",
  "userCount": 0,
  "category": null,
  "lastUpdate": "2019-10-22",
  "creationDate": "2019-10-22",
  "size": 363520,
  "author": "https://preciseplussize.com",
  "smallBanner": "https://lh3.googleusercontent.com/oUNe_9x4EebdFZ3By4rF3Hqbqxqt8O9e5oHmvVzWlCMT7ERKMvM09uF6mFH2y0r65ex0R1a4CwdQI6TXMjoUbz2TvHE",
  "marqueeBanner": null,
  "email": null,
  "emailIsInvalid": null,
  "supportedLanguages": "[\"en\"]",
  "website": "https://preciseplussize.com/",
  "url": "https://chromewebstore.google.com/detail/hello-world/adofikeojceeapelplfkcgommdhnocdi",
  "numScreenshots": 1,
  "numVideos": null,
  "downloadUrl": "https://chrome-stats.com/api/download?id=adofikeojceeapelplfkcgommdhnocdi&version=0.1&type=CRX",
  "isFeatured": null,
  "paymentType": "free",
  "privacyPolicyUrl": null,
  "resurrectionDate": null,
  "previousObsoleteDate": null,
  "publisherAddress": null,
  "publisherCountry": null,
  "isTrustedPublisher": null,
  "isMature": null,
  "byGoogle": null,
  "helpUrl": null,
  "isUnlisted": null,
  "extension-rank": null,
  "theme-rank": null,
  "application-rank": 16382,
  "overall-rank": 172910,
  "manifest_manifest_version": 2,
  "manifest_has_browser_action": null,
  "manifest_has_page_action": null,
  "manifest_minimum_chrome_version": null,
  "manifest_override_homepage": null,
  "manifest_override_search_provider": null,
  "manifest_override_bookmarks": null,
  "manifest_override_history": null,
  "manifest_override_newtab": null,
  "manifest_startup_pages": null,
  "manifest_has_devtools_page": null,
  "manifest_has_commands": null,
  "manifest_has_content_scripts": null,
  "manifest_has_oauth": null,
  "manifest_has_file_browser_handlers": null,
  "manifest_has_nacl_modules": null,
  "manifest_offline_enabled": null,
  "manifest_omnibox_keyword": null,
  "manifest_optional_permissions": null,
  "manifest_permissions": null,
  "manifest_host_permissions": null,
  "manifest_optional_host_permissions": null,
  "manifest_num_site_permissions": null,
  "manifest_web_accessible_resources": null
}