{
  "id": "oedcdhhboalimccbbbjaoodnhkohkenn",
  "name": "Radar Plugin",
  "riskScore": 1,
  "riskImpact": 1,
  "riskLikelihood": 2,
  "logo": "https://lh3.googleusercontent.com/F9T2vQwWW8cLKUgbPwhQeOjFrAXOyzof4uqUdlUp6BzeGsdPNQ5aUN4yIL1Z0N4z9tr4_Mm4bwN-7Jc9jF-zZ3lX7g",
  "fetchId": 20240308,
  "version": "1.0.0.17647",
  "ratingValue": 5,
  "ratingCount": 5,
  "description": "Build to enchance the users experiance and enable them to find realstate properties in a better way",
  "itemCategory": "extension",
  "userCount": 45,
  "category": "productivity/tools",
  "lastUpdate": "2023-09-24",
  "creationDate": "2022-02-18",
  "size": 2327839,
  "author": "melkradar.dev",
  "smallBanner": null,
  "marqueeBanner": null,
  "email": "m.khoshsirat88@gmail.com",
  "emailIsInvalid": null,
  "supportedLanguages": "[\"fa\"]",
  "website": null,
  "url": "https://chromewebstore.google.com/detail/radar-plugin/oedcdhhboalimccbbbjaoodnhkohkenn",
  "numScreenshots": 1,
  "numVideos": null,
  "downloadUrl": "https://chrome-stats.com/api/download?id=oedcdhhboalimccbbbjaoodnhkohkenn&version=1.0.0.17647&type=CRX",
  "isFeatured": null,
  "paymentType": "free",
  "privacyPolicyUrl": null,
  "resurrectionDate": null,
  "previousObsoleteDate": null,
  "publisherAddress": null,
  "publisherCountry": null,
  "isTrustedPublisher": null,
  "isMature": null,
  "byGoogle": null,
  "helpUrl": null,
  "isUnlisted": null,
  "extension-rank": 59406,
  "theme-rank": null,
  "application-rank": null,
  "overall-rank": 78228,
  "manifest_manifest_version": 3,
  "manifest_has_browser_action": null,
  "manifest_has_page_action": null,
  "manifest_minimum_chrome_version": null,
  "manifest_override_homepage": null,
  "manifest_override_search_provider": null,
  "manifest_override_bookmarks": null,
  "manifest_override_history": null,
  "manifest_override_newtab": null,
  "manifest_startup_pages": null,
  "manifest_has_devtools_page": null,
  "manifest_has_commands": null,
  "manifest_has_content_scripts": null,
  "manifest_has_oauth": null,
  "manifest_has_file_browser_handlers": null,
  "manifest_has_nacl_modules": null,
  "manifest_offline_enabled": null,
  "manifest_omnibox_keyword": null,
  "manifest_optional_permissions": null,
  "manifest_permissions": "cookies,activeTab,storage,scripting",
  "manifest_host_permissions": "*://*.melkradar.com/*,*://*.divar.ir/*,*://*.melkradar-dv.ir/*",
  "manifest_optional_host_permissions": null,
  "manifest_num_site_permissions": "NaN",
  "manifest_web_accessible_resources": "[{\"resources\":[\"assets/icons/svg/mlk-icon.svg\",\"assets/icons/png/shaypor-small-vendor.png\",\"assets/icons/png/divar-small-vendor.png\",\"assets/icons/png/hamshahri-small-vendor.png\",\"assets/icons/png/delta-small-vendor.png\",\"assets/icons/png/copy-icon.png\",\"assets/icons/svg/mlk-radar-icon.svg\",\"assets/icons/svg/close-icon-bplugin.svg\",\"assets/icons/svg/radar-adver-icon.svg\",\"assets/icons/svg/radar-customer-icon.svg\",\"assets/icons/svg/add-folder-icon.svg\",\"assets/icons/svg/close-icon10.svg\",\"index.html\",\"assets/lottie/green-loading.json\",\"mainDivar.js\",\"polyfillsDivar.js\",\"runtimeDivar.js\"],\"matches\":[\"http://*/*\",\"https://*/*\"],\"extension_ids\":[]}]"
}