{
  "id": "ocdjaaioccldohbjdbmcaffajammlcmh",
  "name": "Lines",
  "riskScore": 1,
  "riskImpact": 1,
  "riskLikelihood": 1,
  "logo": "https://lh3.googleusercontent.com/ZgE5My4IjxM96vHrfYHhrjlz4Mz5NKXdqnnf7xp6_7h1ZjD_XkLaEDv7TeO2cZyiVjX3yVZD8or30cNvKDodsb2wNA",
  "fetchId": 20240308,
  "version": "1.0.1",
  "ratingValue": 4.666666666666667,
  "ratingCount": 6,
  "description": "Lines is a puzzle game. The goal is to remove balls by forming lines of at least five balls of the same color.",
  "itemCategory": "application",
  "userCount": 464,
  "category": null,
  "lastUpdate": "2014-06-12",
  "creationDate": "2014-06-12",
  "size": 61962,
  "author": "Roman Lytvyn",
  "smallBanner": "https://lh3.googleusercontent.com/o7XK5Ui3nDG_3P4eJ4HZgHFwhuCa3LLn9eTm-8ePlILOSC-lt-uVov3dRQmN4UVw6NgAj5a3F36T83izSNM2xsX_",
  "marqueeBanner": null,
  "email": null,
  "emailIsInvalid": null,
  "supportedLanguages": "[\"en\"]",
  "website": null,
  "url": "https://chromewebstore.google.com/detail/lines/ocdjaaioccldohbjdbmcaffajammlcmh",
  "numScreenshots": 4,
  "numVideos": null,
  "downloadUrl": "https://chrome-stats.com/api/download?id=ocdjaaioccldohbjdbmcaffajammlcmh&version=1.0.1&type=CRX",
  "isFeatured": null,
  "paymentType": "free",
  "privacyPolicyUrl": null,
  "resurrectionDate": null,
  "previousObsoleteDate": null,
  "publisherAddress": null,
  "publisherCountry": null,
  "isTrustedPublisher": null,
  "isMature": null,
  "byGoogle": null,
  "helpUrl": null,
  "isUnlisted": null,
  "extension-rank": null,
  "theme-rank": null,
  "application-rank": 4765,
  "overall-rank": 38585,
  "manifest_manifest_version": 2,
  "manifest_has_browser_action": null,
  "manifest_has_page_action": null,
  "manifest_minimum_chrome_version": null,
  "manifest_override_homepage": null,
  "manifest_override_search_provider": null,
  "manifest_override_bookmarks": null,
  "manifest_override_history": null,
  "manifest_override_newtab": null,
  "manifest_startup_pages": null,
  "manifest_has_devtools_page": null,
  "manifest_has_commands": null,
  "manifest_has_content_scripts": null,
  "manifest_has_oauth": null,
  "manifest_has_file_browser_handlers": null,
  "manifest_has_nacl_modules": null,
  "manifest_offline_enabled": true,
  "manifest_omnibox_keyword": null,
  "manifest_optional_permissions": null,
  "manifest_permissions": "notifications",
  "manifest_host_permissions": null,
  "manifest_optional_host_permissions": null,
  "manifest_num_site_permissions": null,
  "manifest_web_accessible_resources": null
}