{
  "id": "lmmkabdibcnmjolemacgimkiakgopiga",
  "name": "MentiPlus",
  "riskScore": 0,
  "riskImpact": 1,
  "riskLikelihood": 1,
  "logo": "https://lh3.googleusercontent.com/FGAakTmZSPNbOT8_NUSFEajwmqwf4-frmun1FVPuI6TkdlLa7A3FIaqWs76NEbO2BigmJRQxOsmwnccbhuwAxhFgkQ",
  "fetchId": 20240308,
  "version": "4.9.12",
  "ratingValue": 0,
  "ratingCount": 0,
  "description": "Mentimeter formatting extension. Change a graph column's colour or the format of the axis text using a contextual menu",
  "itemCategory": "extension",
  "userCount": 4000,
  "category": "productivity/communication",
  "lastUpdate": "2024-02-09",
  "creationDate": "2020-07-01",
  "size": 1971323,
  "author": "https://oldpike.bxtrom.eu",
  "smallBanner": null,
  "marqueeBanner": null,
  "email": "oldpikesoftware@gmail.com",
  "emailIsInvalid": null,
  "supportedLanguages": "[\"en-GB\"]",
  "website": "https://oldpike.bxtrom.eu/",
  "url": "https://chromewebstore.google.com/detail/mentiplus/lmmkabdibcnmjolemacgimkiakgopiga",
  "numScreenshots": 5,
  "numVideos": 1,
  "downloadUrl": "https://chrome-stats.com/api/download?id=lmmkabdibcnmjolemacgimkiakgopiga&version=4.9.12&type=CRX",
  "isFeatured": true,
  "paymentType": "free",
  "privacyPolicyUrl": "https://oldpike.bxtrom.eu/privacy_policy.html",
  "resurrectionDate": null,
  "previousObsoleteDate": null,
  "publisherAddress": null,
  "publisherCountry": null,
  "isTrustedPublisher": true,
  "isMature": null,
  "byGoogle": null,
  "helpUrl": "https://oldpike.bxtrom.eu/",
  "isUnlisted": null,
  "extension-rank": 13116,
  "theme-rank": null,
  "application-rank": null,
  "overall-rank": 16146,
  "manifest_manifest_version": 3,
  "manifest_has_browser_action": null,
  "manifest_has_page_action": null,
  "manifest_minimum_chrome_version": null,
  "manifest_override_homepage": null,
  "manifest_override_search_provider": null,
  "manifest_override_bookmarks": null,
  "manifest_override_history": null,
  "manifest_override_newtab": null,
  "manifest_startup_pages": null,
  "manifest_has_devtools_page": null,
  "manifest_has_commands": null,
  "manifest_has_content_scripts": true,
  "manifest_has_oauth": null,
  "manifest_has_file_browser_handlers": null,
  "manifest_has_nacl_modules": null,
  "manifest_offline_enabled": null,
  "manifest_omnibox_keyword": null,
  "manifest_optional_permissions": null,
  "manifest_permissions": "storage",
  "manifest_host_permissions": "https://bxtrom.eu/stats/mentiplus-stats/*",
  "manifest_optional_host_permissions": null,
  "manifest_num_site_permissions": "NaN",
  "manifest_web_accessible_resources": "[{\"resources\":[\"scales_1.png\",\"scales_2.png\",\"dots.png\",\"menu_1.png\",\"menu_2.png\",\"mt1.png\",\"mt2.png\",\"mt3.png\",\"mt4.png\",\"mt5.png\",\"mt6.png\",\"disable.png\",\"opts_0.png\",\"opts_1.png\",\"opts_2.png\",\"opts_3.png\",\"opts_4.png\",\"options.html\",\"icon.jpeg\",\"manual.js\",\"focusFrame.png\",\"focusFrame_2.png\",\"disableMenuItem.png\",\"disableDemo.png\",\"mentImage.png\",\"inactivate.png\"],\"matches\":[\"https://www.mentimeter.com/*\"]}]"
}