{
  "id": "oomijgnfikpndibbbbaninbfomjddohj",
  "name": "LiveKeyword by BiQ",
  "riskScore": 0,
  "riskImpact": 2,
  "riskLikelihood": 0,
  "logo": "https://lh3.googleusercontent.com/aUS5f4lojVHc-8aeylTAeNe0T6yHB9YKjgtQykOaQb5jGvfIpRLaeyDSf0PhQKsEX6aXV6frz70GGnFu41sXljZZ",
  "fetchId": 20240308,
  "version": "1.4.1",
  "ratingValue": 4,
  "ratingCount": 12,
  "description": "Keyword search volume, CPC, and competition for Google™ Search Engine Result Page (SERP).",
  "itemCategory": "extension",
  "userCount": 3000,
  "category": "productivity/workflow",
  "lastUpdate": "2022-02-18",
  "creationDate": "2020-06-08",
  "size": 222208,
  "author": "Meta Dev",
  "smallBanner": "https://lh3.googleusercontent.com/_rucWcJ9nPioDiRrt_ZQv4NFxHxmDsPNddPTXAOxZpgF-gvaJD064sWF0QLZvAsd4Iy2XgDxsIy5cMQGC2tlawQoiEI",
  "marqueeBanner": null,
  "email": "metasupport@plentisoft.com",
  "emailIsInvalid": null,
  "supportedLanguages": "[\"en\"]",
  "website": "https://biq.cloud/live-keyword/",
  "url": "https://chromewebstore.google.com/detail/livekeyword-by-biq/oomijgnfikpndibbbbaninbfomjddohj",
  "numScreenshots": 5,
  "numVideos": null,
  "downloadUrl": "https://chrome-stats.com/api/download?id=oomijgnfikpndibbbbaninbfomjddohj&version=1.4.1&type=CRX",
  "isFeatured": true,
  "paymentType": "free",
  "privacyPolicyUrl": null,
  "resurrectionDate": null,
  "previousObsoleteDate": null,
  "publisherAddress": null,
  "publisherCountry": null,
  "isTrustedPublisher": true,
  "isMature": null,
  "byGoogle": null,
  "helpUrl": "https://biq.cloud/live-keyword/",
  "isUnlisted": null,
  "extension-rank": 13997,
  "theme-rank": null,
  "application-rank": null,
  "overall-rank": 17391,
  "manifest_manifest_version": 2,
  "manifest_has_browser_action": true,
  "manifest_has_page_action": null,
  "manifest_minimum_chrome_version": null,
  "manifest_override_homepage": null,
  "manifest_override_search_provider": null,
  "manifest_override_bookmarks": null,
  "manifest_override_history": null,
  "manifest_override_newtab": null,
  "manifest_startup_pages": null,
  "manifest_has_devtools_page": null,
  "manifest_has_commands": null,
  "manifest_has_content_scripts": true,
  "manifest_has_oauth": null,
  "manifest_has_file_browser_handlers": null,
  "manifest_has_nacl_modules": null,
  "manifest_offline_enabled": null,
  "manifest_omnibox_keyword": null,
  "manifest_optional_permissions": null,
  "manifest_permissions": "storage,activeTab",
  "manifest_host_permissions": null,
  "manifest_optional_host_permissions": null,
  "manifest_num_site_permissions": 1,
  "manifest_web_accessible_resources": "[\"/img/*\"]"
}